[{"id":"6281534162316@s.whatsapp.net","xp":1,"level":1},{"id":"6285694347823@s.whatsapp.net","xp":1,"level":1},{"id":"6285849004978@s.whatsapp.net","xp":1,"level":1},{"id":"6281340991006@s.whatsapp.net","xp":1,"level":1},{"id":"6288270863155@s.whatsapp.net","xp":1,"level":1},{"id":"6285779000268@s.whatsapp.net","xp":1,"level":1},{"id":"6285814267893@s.whatsapp.net","xp":1,"level":1},{"id":"6281227825649@s.whatsapp.net","xp":1,"level":1},{"id":"6285756186082@s.whatsapp.net","xp":1,"level":1},{"id":"62895344554277@s.whatsapp.net","xp":1,"level":1}]